docparser/__init__.py
docparser/core.py
docparser/parser.py
documentparser-1.0a1.dist-info/METADATA
documentparser-1.0a1.dist-info/RECORD
documentparser-1.0a1.dist-info/WHEEL
documentparser-1.0a1.dist-info/top_level.txt
