Metadata-Version: 2.1
Name: documentparser
Version: 1.0a1
Summary: A simple CLI tool that allow to extract all text contained into a document.
Home-page: https://github.com/RobyFerro/DocumentParser
Author: Roberto Ferro
Author-email: roberto.ferro@ikdev.eu
License: UNKNOWN
Platform: UNKNOWN
Classifier: Programming Language :: Python :: 2.7
Classifier: License :: OSI Approved :: MIT License
Classifier: Operating System :: OS Independent
